MANIFEST.in
README.md
README.rst
setup.py
.git/modules/fastText/HEAD
src/args.itm
src/compat.h
src/custom_exit.h
src/fasttext_access.cpp
src/fasttext_access.h
src/private_access.h
src/pyfasttext.cpp
src/pyfasttext.pyx
src/fastText/src/args.cc
src/fastText/src/args.h
src/fastText/src/dictionary.cc
src/fastText/src/dictionary.h
src/fastText/src/fasttext.cc
src/fastText/src/fasttext.h
src/fastText/src/main.cc
src/fastText/src/matrix.cc
src/fastText/src/matrix.h
src/fastText/src/model.cc
src/fastText/src/model.h
src/fastText/src/productquantizer.cc
src/fastText/src/productquantizer.h
src/fastText/src/qmatrix.cc
src/fastText/src/qmatrix.h
src/fastText/src/real.h
src/fastText/src/utils.cc
src/fastText/src/utils.h
src/fastText/src/vector.cc
src/fastText/src/vector.h
src/pyfasttext.egg-info/PKG-INFO
src/pyfasttext.egg-info/SOURCES.txt
src/pyfasttext.egg-info/dependency_links.txt
src/pyfasttext.egg-info/requires.txt
src/pyfasttext.egg-info/top_level.txt
src/variant/include/mapbox/optional.hpp
src/variant/include/mapbox/recursive_wrapper.hpp
src/variant/include/mapbox/variant.hpp
src/variant/include/mapbox/variant_cast.hpp
src/variant/include/mapbox/variant_io.hpp
src/variant/include/mapbox/variant_visitor.hpp
src/variant/test/bench_variant.cpp
src/variant/test/binary_visitor_test.cpp
src/variant/test/boost_variant_hello_world.cpp
src/variant/test/hashable_test.cpp
src/variant/test/lambda_overload_test.cpp
src/variant/test/our_variant_hello_world.cpp
src/variant/test/recursive_wrapper_test.cpp
src/variant/test/reference_wrapper_test.cpp
src/variant/test/unique_ptr_test.cpp
src/variant/test/unit.cpp
src/variant/test/compilation_failure/default_constructor.cpp
src/variant/test/compilation_failure/empty_typelist.cpp
src/variant/test/compilation_failure/equality.cpp
src/variant/test/compilation_failure/get_type.cpp
src/variant/test/compilation_failure/is_type.cpp
src/variant/test/compilation_failure/mutating_visitor_on_const.cpp
src/variant/test/compilation_failure/no-reference.cpp
src/variant/test/include/auto_cpu_timer.hpp
src/variant/test/include/catch.hpp
src/variant/test/t/binary_visitor_1.cpp
src/variant/test/t/binary_visitor_2.cpp
