Metadata-Version: 1.1
Name: pyfasttext
Version: 0.4.5
Summary: Yet another Python binding for fastText
Home-page: https://github.com/vrasneur/pyfasttext
Author: Vincent Rasneur
Author-email: vrasneur@free.fr
License: GPLv3
Download-URL: https://github.com/vrasneur/pyfasttext/releases/download/0.4.5/pyfasttext-0.4.5.tar.gz
Platform: UNKNOWN
Classifier: Development Status :: 3 - Alpha
Classifier: Intended Audience :: Developers
Classifier: Intended Audience :: Science/Research
Classifier: License :: OSI Approved :: GNU General Public License v3 (GPLv3)
Classifier: Operating System :: POSIX
Classifier: Programming Language :: C++
Classifier: Programming Language :: Cython
Classifier: Programming Language :: Python :: 2.6
Classifier: Programming Language :: Python :: 2.7
Classifier: Programming Language :: Python :: 3
Classifier: Topic :: Scientific/Engineering :: Artificial Intelligence
